llama_trainer/__init__.py
llama_trainer/infer.py
llama_trainer/trainer.py
llama_trainer/version.py
llama_trainer/cli/__init__.py
llama_trainer/cli/train.py
llama_trainer/utils/__init__.py
llama_trainer/utils/llama_patch.py
llama_trainer/utils/stopping_criteria.py
llama_trainer-0.2.1.dist-info/METADATA
llama_trainer-0.2.1.dist-info/WHEEL
llama_trainer-0.2.1.dist-info/top_level.txt
llama_trainer-0.2.1.dist-info/RECORD
