Metadata-Version: 2.1
Name: llama-trainer
Version: 0.2.1
Summary: Llama trainer utility
Home-page: https://github.com/Riccorl/llama-trainer
Author: Riccardo Orlando
Author-email: orlandorcc@gmail.com
License: Apache
Keywords: NLP deep learning transformer pytorch llama llms hf huggingface
Classifier: Intended Audience :: Science/Research
Classifier: License :: OSI Approved :: Apache Software License
Classifier: Programming Language :: Python :: 3
Classifier: Topic :: Scientific/Engineering :: Artificial Intelligence
Requires-Python: >=3.10
Requires-Dist: torch <2.1,>=1.10
Requires-Dist: accelerate <0.23,>=0.21
Requires-Dist: peft <0.5,>=0.4
Requires-Dist: bitsandbytes ==0.40.2
Requires-Dist: transformers <5.1,>=4.31
Requires-Dist: trl ==0.4.7
Requires-Dist: scipy
Requires-Dist: black
